{
  "caseStudies": [
    {
      "slug": "clientname",
      "sections": [
        {
          "name": "CaseStudyBanner",
          "backgroundImage": "https://via.placeholder.com/2000x800",
          "textContent": "<h1 class='text-5xl mb-5'>Testing title</h1><p>testing body content</p>"
        },
        {
          "name": "CaseStudyGrid",
          "columns": [
            {
              "widthClass": "w-2/5",
              "content": "<p>html content</p>"
            },
            {
              "widthClass": "w-3/5",
              "content": "<p>html content</p>"
            }
          ]
        },
        {
          "name": "CaseStudyGrid",
          "columns": [
            {
              "widthClass": "w-100",
              "content": "<img src='https://via.placeholder.com/2000x800'>"
            }
          ],
          "backgroundElement": {
            "widthClass": "full-width",
            "heightClass": "half-height",
            "color": "#f4f4f4",
            "positionClass": "left-0 bottom-0"
          }
        },
        {
          "name": "CaseStudyGrid",
          "columns": [
            {
              "widthClass": "w-2/5",
              "content": "<p>html content</p>"
            },
            {
              "widthClass": "w-3/5",
              "content": "<p>html content</p>"
            }
          ],
          "backgroundElement": {
            "widthClass": "full-width",
            "heightClass": "full-height",
            "color": "#f4f4f4",
            "positionClass": "left-0 bottom-0"
          }
        }
      ]
    }
  ]
}
